dataset_up/__init__.py
dataset_up/cli.py
dataset_up/api/AuthApi.py
dataset_up/api/DatasetApi.py
dataset_up/api/__init__.py
dataset_up/client/AuthClient.py
dataset_up/client/Client.py
dataset_up/client/__init__.py
dataset_up/config/__init__.py
dataset_up/config/constants.py
dataset_up/config/login_config.py
dataset_up/config/path_config.py
dataset_up/log/__init__.py
dataset_up/log/logger.py
dataset_up/update/__init__.py
dataset_up/update/sdk_version.py
dataset_up/update/update_check.py
dataset_up/uploader/__init__.py
dataset_up/uploader/upload_context.py
dataset_up/uploader/uploaded_file.py
dataset_up/uploader/uploader.py
dataset_up/utils/__init__.py
dataset_up/utils/concurrent_utils.py
dataset_up/utils/file.py
dataset_up/utils/http_utils.py
dataset_up/utils/interrupt_utils.py
dataset_up/utils/output_format.py
dataset_up/utils/retryable.py
dataset_up/utils/sliding_window_speed_calculator.py
dataset_up/utils/system_utils.py
dataset_up/utils/time_utils.py
zyd_dataset_up-0.17.0.dist-info/METADATA
zyd_dataset_up-0.17.0.dist-info/WHEEL
zyd_dataset_up-0.17.0.dist-info/entry_points.txt
zyd_dataset_up-0.17.0.dist-info/top_level.txt
zyd_dataset_up-0.17.0.dist-info/RECORD
